mseep_mcp_atlassian-1.0.1.dist-info/licenses/LICENSE
tests/__init__.py
tests/conftest.py
tests/test_preprocessing.py
tests/test_real_api_validation.py
tests/fixtures/__init__.py
tests/fixtures/confluence_mocks.py
tests/fixtures/jira_mocks.py
tests/utils/__init__.py
tests/utils/assertions.py
tests/utils/base.py
tests/utils/factories.py
tests/utils/mocks.py
mseep_mcp_atlassian-1.0.1.dist-info/METADATA
mseep_mcp_atlassian-1.0.1.dist-info/WHEEL
mseep_mcp_atlassian-1.0.1.dist-info/top_level.txt
mseep_mcp_atlassian-1.0.1.dist-info/RECORD
